LICENSE
README.md
setup.cfg
setup.py
hentai_chan_api_async/__init__.py
hentai_chan_api_async/data.py
hentai_chan_api_async/hentaichan.py
hentai_chan_api_async/http.py
hentai_chan_api_async.egg-info/PKG-INFO
hentai_chan_api_async.egg-info/SOURCES.txt
hentai_chan_api_async.egg-info/dependency_links.txt
hentai_chan_api_async.egg-info/requires.txt
hentai_chan_api_async.egg-info/top_level.txt
hentai_chan_api_async/parsers/__init__.py
hentai_chan_api_async/parsers/content.py
hentai_chan_api_async/parsers/page.py